climemu/__init__.py
climemu/emulators/__init__.py
climemu/emulators/abstractemulator.py
climemu/emulators/bouabid2025.py
climemu/utils/__init__.py
climemu/utils/registry.py
climemu-0.1.8.dist-info/licenses/LICENSE
datasets/__init__.py
datasets/cmip6.py
datasets/constants.py
datasets/pattern_to_cmip6.py
diffusion/__init__.py
diffusion/losses/__init__.py
diffusion/losses/denoising_score_matching.py
diffusion/nn/__init__.py
diffusion/nn/healpixunet.py
diffusion/nn/backbones/__init__.py
diffusion/nn/backbones/convnet.py
diffusion/nn/modules/__init__.py
diffusion/nn/modules/remap.py
diffusion/nn/modules/healpix/__init__.py
diffusion/nn/modules/healpix/conv.py
diffusion/nn/modules/healpix/padding.py
diffusion/nn/timeencoder/__init__.py
diffusion/nn/timeencoder/gaussianfourier.py
diffusion/samplers/__init__.py
diffusion/samplers/continuous_ode_sampler.py
diffusion/schedules/__init__.py
diffusion/schedules/variance_exploding.py
utils/__init__.py
utils/collate.py
utils/arrays/__init__.py
utils/arrays/aggregate.py
utils/arrays/convert.py
utils/arrays/filter.py
utils/arrays/reshape.py
utils/arrays/smooth.py
utils/graphs/__init__.py
utils/graphs/haversine.py
climemu-0.1.8.dist-info/METADATA
climemu-0.1.8.dist-info/WHEEL
climemu-0.1.8.dist-info/top_level.txt
climemu-0.1.8.dist-info/RECORD
