Metadata-Version: 2.4
Name: climemu
Version: 0.1.8
Summary: Score-based generative emulation of impact-relevant earth system model outputs
Author-email: Shahine Bouabid <shahineb@mit.edu>
License: MIT
Requires-Python: >=3.11
License-File: LICENSE
Requires-Dist: diffrax>=0.7.0
Requires-Dist: einops>=0.8.1
Requires-Dist: equinox>=0.13.0
Requires-Dist: huggingface-hub>=0.35.0
Requires-Dist: jax>=0.7.1
Requires-Dist: netcdf4>=1.7.2
Requires-Dist: numpy>=2.3.2
Requires-Dist: xarray>=2025.9.0
Provides-Extra: gpu
Requires-Dist: jax[cuda12]>=0.7.1; extra == "gpu"
Provides-Extra: train
Requires-Dist: dask>=2025.7.0; extra == "train"
Requires-Dist: torch>=2.8.0; extra == "train"
Requires-Dist: healpy>=1.18.1; extra == "train"
Requires-Dist: optax>=0.2.5; extra == "train"
Requires-Dist: scikit-learn>=1.7.1; extra == "train"
Requires-Dist: scipy>=1.16.1; extra == "train"
Requires-Dist: tqdm>=4.67.1; extra == "train"
Requires-Dist: wandb>=0.21.3; extra == "train"
Provides-Extra: plots
Requires-Dist: matplotlib>=3.10.6; extra == "plots"
Requires-Dist: seaborn>=0.13.2; extra == "plots"
Requires-Dist: cartopy>=0.25.0; extra == "plots"
Requires-Dist: regionmask>=0.13.0; extra == "plots"
Requires-Dist: pandas>=2.3.2; extra == "plots"
Requires-Dist: pyshtools>=4.13.1; extra == "plots"
Provides-Extra: test
Requires-Dist: pytest>=8.0.0; extra == "test"
Requires-Dist: pytest-cov>=4.0.0; extra == "test"
Requires-Dist: pytest-mock>=3.10.0; extra == "test"
Requires-Dist: jaxlib>=0.4.0; extra == "test"
Dynamic: license-file
